LICENSE
MANIFEST.in
README.md
setup.py
ProTstab2/__init__.py
ProTstab2/utils.py
ProTstab2.egg-info/PKG-INFO
ProTstab2.egg-info/SOURCES.txt
ProTstab2.egg-info/dependency_links.txt
ProTstab2.egg-info/requires.txt
ProTstab2.egg-info/top_level.txt
ProTstab2/ProtDCal/PropertyIndices.idx
ProTstab2/ProtDCal/ProtDCal-parallel.pl
ProTstab2/ProtDCal/ProtDCal.jar
ProTstab2/ProtDCal/abhishek_project_corrected.proj
ProTstab2/ProtDCal/build.xml
ProTstab2/ProtDCal/groups.gdm
ProTstab2/ProtDCal/manifest.mf
ProTstab2/ProtDCal/parameter.cfg
ProTstab2/ProtDCal/release-notes_v4.txt
ProTstab2/ProtDCal/Datasets/example_pairs.ppi
ProTstab2/ProtDCal/Datasets/Fasta_Protein_Format/SYC1_MYCTU.txt
ProTstab2/ProtDCal/Datasets/Fasta_Protein_Format/example_data.fasta
ProTstab2/ProtDCal/Datasets/Fasta_Protein_Format/p00001.txt
ProTstab2/ProtDCal/Datasets/Pdb_Protein_Format/1BNI_A.pdb
ProTstab2/ProtDCal/Datasets/Pdb_Protein_Format/1CSP.pdb
ProTstab2/ProtDCal/Datasets/Pdb_Protein_Format/1DIV_c.pdb
ProTstab2/ProtDCal/Datasets/Pdb_Protein_Format/1DIV_n.pdb
ProTstab2/ProtDCal/Datasets/Pdb_Protein_Format/1E0L_W30.pdb
ProTstab2/ProtDCal/Datasets/Pdb_Protein_Format/1FNF_10.pdb
ProTstab2/ProtDCal/Datasets/Pdb_Protein_Format/1FNF_9.pdb
ProTstab2/ProtDCal/Datasets/Pdb_Protein_Format/1LMB_red.pdb
ProTstab2/ProtDCal/Datasets/Pdb_Protein_Format/1N88.pdb
ProTstab2/ProtDCal/Datasets/Pdb_Protein_Format/1RFA.pdb
ProTstab2/ProtDCal/Datasets/Pdb_Protein_Format/1RIS.pdb
ProTstab2/ProtDCal/Datasets/Pdb_Protein_Format/1SHG.pdb
ProTstab2/ProtDCal/Datasets/Pdb_Protein_Format/1UBQ.pdb
ProTstab2/ProtDCal/Datasets/Pdb_Protein_Format/1jmq_A_K30L.pdb
ProTstab2/ProtDCal/Datasets/Pdb_Protein_Format/1rlq_C.pdb
ProTstab2/ProtDCal/Datasets/Pdb_Protein_Format/2CI2.pdb
ProTstab2/ProtDCal/Help/guide.hs
ProTstab2/ProtDCal/Help/guideidx.hs
ProTstab2/ProtDCal/Help/jhindexer
ProTstab2/ProtDCal/Help/jhindexer.bat
ProTstab2/ProtDCal/Help/jhindexer.jar
ProTstab2/ProtDCal/Help/jhsearch
ProTstab2/ProtDCal/Help/jhsearch.bat
ProTstab2/ProtDCal/Help/jhsearch.jar
ProTstab2/ProtDCal/Help/tree.xml
ProTstab2/ProtDCal/Help/treeidx.xml
ProTstab2/ProtDCal/Help/urls.jhm
ProTstab2/ProtDCal/Help/urlsidx.jhm
