Metadata-Version: 2.1
Name: ProTstab2
Version: 2.0.2
Summary: Protein prediction package
Home-page: http://8.133.174.28:8000
Author: Jianjun Zhao
Author-email: 20204227057@stu.suda.edu.cn
License: MIT
Platform: all
Classifier: Intended Audience :: Developers
Classifier: Operating System :: OS Independent
Classifier: Programming Language :: Python :: 3
Classifier: License :: OSI Approved :: MIT License
Requires-Python: >=3.6
License-File: LICENSE
